pywebhost/__init__.py
pywebhost/handler/__init__.py
pywebhost/modules/__init__.py
pywebhost/modules/session.py
pywebhost/modules/websocket.py
pywebhost-1.3.0.0.dist-info/LICENSE
pywebhost-1.3.0.0.dist-info/METADATA
pywebhost-1.3.0.0.dist-info/WHEEL
pywebhost-1.3.0.0.dist-info/top_level.txt
pywebhost-1.3.0.0.dist-info/RECORD
