Metadata-Version: 2.1
Name: pywebhost
Version: 1.3.0.0
Summary: A versatile webserver written in Python 3
Home-page: https://github.com/greats3an/pywebhost
Author: greats3an
Author-email: greats3an@gmail.com
License: UNKNOWN
Platform: UNKNOWN
Classifier: Programming Language :: Python :: 3
Classifier: License :: OSI Approved :: Apache Software License
Classifier: Operating System :: OS Independent
Requires-Python: >=3.6
License-File: LICENSE
